SwimScraper/SwimScraper.py
SwimScraper/__init__.py
SwimScraper/getTeamList.py
SwimScraper-0.0.4.dist-info/LICENSE
SwimScraper-0.0.4.dist-info/METADATA
SwimScraper-0.0.4.dist-info/WHEEL
SwimScraper-0.0.4.dist-info/top_level.txt
SwimScraper-0.0.4.dist-info/RECORD
