Metadata-Version: 2.1
Name: SwimScraper
Version: 0.0.4
Summary: A package to scrape professional and college swimming data.
Home-page: https://github.com/maflancer/SwimScraper
Author: Matthew Flancer
Author-email: maf291@pitt.edu
License: UNKNOWN
Project-URL: Bug Tracker, https://github.com/maflancer/SwimScraper/issues
Platform: UNKNOWN
Classifier: Programming Language :: Python :: 3
Classifier: License :: OSI Approved :: MIT License
Classifier: Operating System :: OS Independent
Requires-Python: >=3.6
License-File: LICENSE
Requires-Dist: requests
Requires-Dist: csv
Requires-Dist: bs4
Requires-Dist: pandas
Requires-Dist: selenium
Requires-Dist: time
Requires-Dist: webdriver-manager
